sxsdiff/__init__.py
sxsdiff/calculator.py
sxsdiff/generators/__init__.py
sxsdiff/generators/github.py
sxsdiff-0.3.0.dist-info/DESCRIPTION.rst
sxsdiff-0.3.0.dist-info/METADATA
sxsdiff-0.3.0.dist-info/metadata.json
sxsdiff-0.3.0.dist-info/RECORD
sxsdiff-0.3.0.dist-info/top_level.txt
sxsdiff-0.3.0.dist-info/WHEEL
